AUTHORS
CHANGELOG.txt
DESCRIPTION
LICENCE
MANIFEST.in
README.md
setup.py
basitapi/__init__.py
basitapi/__init__.pyc
basitapi/decorators.py
basitapi/decorators.pyc
basitapi/exception.py
basitapi/exception.pyc
basitapi/response.py
basitapi/response.pyc
basitapi/urlpatterns.py
basitapi/urlpatterns.pyc
basitapi/views.py
basitapi/views.pyc
basitapi.egg-info/PKG-INFO
basitapi.egg-info/SOURCES.txt
basitapi.egg-info/dependency_links.txt
basitapi.egg-info/requires.txt
basitapi.egg-info/top_level.txt
basitapi/tests/__init__.py
basitapi/tests/__init__.pyc
basitapi/tests/exception_tests.py
basitapi/tests/exception_tests.pyc
basitapi/tests/factories.py
basitapi/tests/factories.pyc
basitapi/tests/response_tests.py
basitapi/tests/response_tests.pyc
basitapi/tests/runtests.py
basitapi/tests/runtests.pyc
basitapi/tests/urlpatterns_tests.py
basitapi/tests/urlpatterns_tests.pyc
basitapi/tests/urls.py
basitapi/tests/urls.pyc
basitapi/tests/integration_tests/__init__.py
basitapi/tests/integration_tests/__init__.pyc
basitapi/tests/integration_tests/views_tests.py
basitapi/tests/integration_tests/views_tests.pyc