Metadata-Version: 1.0
Name: basitapi
Version: 0.1
Summary: UNKNOWN
Home-page: https://github.com/omerucel/basitapi
Author: Ömer ÜCEL
Author-email: omerucel@gmail.com
License: The MIT LICENCE
Keywords: rest,api,django
Platform: UNKNOWN
